conversationalist/__init__.py
conversationalist/adapters.py
conversationalist/classes.py
conversationalist/client.py
conversationalist/conversationalist.py
conversationalist/core.py
conversationalist/main.py
conversationalist/settings.py
conversationalist/utils.py
conversationalist/templates/tick_tock.html
conversationalist/templates/tick_tock_body.html
conversationalist-0.1.1.dist-info/DESCRIPTION.rst
conversationalist-0.1.1.dist-info/METADATA
conversationalist-0.1.1.dist-info/RECORD
conversationalist-0.1.1.dist-info/WHEEL
conversationalist-0.1.1.dist-info/metadata.json
conversationalist-0.1.1.dist-info/top_level.txt
