Metadata-Version: 2.0
Name: conversationalist
Version: 0.1.1
Summary: Converts tweet streams into an organized, story-telling web-page .
Home-page: https://github.com/jga/conversationalist
Author: Julio Gonzalez Altamirano
Author-email: devjga@gmail.com
License: MIT
Keywords: python twitter
Platform: Any
Classifier: License :: OSI Approved :: MIT License
Classifier: Intended Audience :: Developers
Classifier: Programming Language :: Python :: 3 :: Only
Requires-Dist: python-dateutil
Requires-Dist: pytz
Requires-Dist: tweepy
